[
    { "location": "London", "latitude": 51.5073219, "longitude": -0.1276474 },
    { "location": "Dhaka", "latitude": 23.777176, "longitude": 90.399452 },
    { "location": "Singapore", "latitude": 1.2899175, "longitude": 103.8519072 },
    { "location": "NewYork", "latitude": 40.7127281, "longitude": -74.0060152 },
    { "location": "Toronto", "latitude": 43.6534817, "longitude": -79.3839347 },
    { "location": "Tokyo", "latitude": 35.6894875, "longitude": 139.6917064 },
    { "location": "Paris", "latitude": 48.8566101, "longitude": 2.3514992 },
    { "location": "Sydney", "latitude": -33.8688197, "longitude": 151.2092955 },
    { "location": "Mumbai", "latitude": 19.0759837, "longitude": 72.8776559 },
    { "location": "Moscow", "latitude": 55.755826, "longitude": 37.6172999 },
    { "location": "Bangkok", "latitude": 13.7563309, "longitude": 100.5017651 },
    { "location": "Dubai", "latitude": 25.276987, "longitude": 55.296249 }
]
